tk_html_widgets/__init__.py
tk_html_widgets/html_parser.py
tk_html_widgets-0.3.0.dist-info/LICENSE
tk_html_widgets-0.3.0.dist-info/METADATA
tk_html_widgets-0.3.0.dist-info/WHEEL
tk_html_widgets-0.3.0.dist-info/top_level.txt
tk_html_widgets-0.3.0.dist-info/RECORD
