Metadata-Version: 2.1
Name: tk-html-widgets
Version: 0.3.0
Summary: HTML widgets for tkinter
Home-page: https://github.com/paolo-gurisatti/tk_html_widgets
Author: Paolo Gurisatti
Author-email: paolo@fastmail.com
License: UNKNOWN
Platform: UNKNOWN
Classifier: Programming Language :: Python :: 3
Classifier: License :: OSI Approved :: MIT License
Classifier: Operating System :: OS Independent
Requires-Python: >=3.4.*
Requires-Dist: Pillow (>=5.3.0)
